pg13/__init__.py
pg13/__init__.pyc
pg13/diff.py
pg13/diff.pyc
pg13/errors.py
pg13/errors.pyc
pg13/misc.py
pg13/misc.pyc
pg13/pg.py
pg13/pg.pyc
pg13/pgmock.py
pg13/pgmock.pyc
pg13/pgmock_dbapi2.py
pg13/pool_psyco.py
pg13/redismodel.py
pg13/sqex.py
pg13/sqex.pyc
pg13/sqla.py
pg13/sqparse2.py
pg13/sqparse2.pyc
pg13/stubredis.py
pg13/syncmessage.py
pg13/syncmessage.pyc
pg13/syncschema.py
pg13/syncschema.pyc
pg13/threevl.py
pg13/threevl.pyc
pg13/treepath.py
pg13-0.1.1.dist-info/DESCRIPTION.rst
pg13-0.1.1.dist-info/METADATA
pg13-0.1.1.dist-info/metadata.json
pg13-0.1.1.dist-info/RECORD
pg13-0.1.1.dist-info/top_level.txt
pg13-0.1.1.dist-info/WHEEL
test_pg13/__init__.py
test_pg13/__init__.pyc
test_pg13/test_dbapi2.py
test_pg13/test_diff.py
test_pg13/test_misc.py
test_pg13/test_pg.py
test_pg13/test_pgmock.py
test_pg13/test_redismodel.py
test_pg13/test_sqex.py
test_pg13/test_sqla.py
test_pg13/test_sqparse.py
test_pg13/test_sqparse2.py
test_pg13/test_syncschema.py
test_pg13/test_threevl.py
test_pg13/test_treepath.py
test_pg13/__pycache__/test_diff.cpython-27-PYTEST.pyc
test_pg13/__pycache__/test_misc.cpython-27-PYTEST.pyc
test_pg13/__pycache__/test_pg.cpython-27-PYTEST.pyc
test_pg13/__pycache__/test_pgmock.cpython-27-PYTEST.pyc
test_pg13/__pycache__/test_sqex.cpython-27-PYTEST.pyc
test_pg13/__pycache__/test_sqparse.cpython-27-PYTEST.pyc
test_pg13/__pycache__/test_sqparse2.cpython-27-PYTEST.pyc
test_pg13/__pycache__/test_syncschema.cpython-27-PYTEST.pyc
test_pg13/__pycache__/test_threevl.cpython-27-PYTEST.pyc
