Metadata-Version: 2.0
Name: pg13
Version: 0.1.1
Summary: sql evaluator for mocking
Home-page: https://github.com/abe-winter/pg13-py
Author: Abe Winter
Author-email: abe-winter@users.noreply.github.com
License: MIT
Keywords: sql,mocking,orm,database,testing
Platform: UNKNOWN
Classifier: Development Status :: 4 - Beta
Classifier: License :: OSI Approved :: MIT License
Classifier: Programming Language :: Python :: 2.7
Classifier: Programming Language :: Python :: 2 :: Only
Classifier: Topic :: Database
Classifier: Topic :: Software Development :: Interpreters
Classifier: Topic :: Software Development :: Testing
Requires-Dist: pytest
Requires-Dist: ujson
Requires-Dist: ply
Provides-Extra: sqla
Requires-Dist: sqlalchemy; extra == 'sqla'
Provides-Extra: psyco
Requires-Dist: psycopg2; extra == 'psyco'
Provides-Extra: redis
Requires-Dist: hiredis; extra == 'redis'
Requires-Dist: redis; extra == 'redis'
Requires-Dist: msgpack-python; extra == 'redis'
